{"comments_archived":true,"date":"2002-12-01T00:00:00.000Z","layout":"post","title":"example.com is not porn - yay!","wordpress_id":313,"wordpress_slug":"ooocci","wordpress_url":"http://www.decafbad.com/blog/?p=313","url":"/2002/12/01/ooocci/","summary":"<p>Noticed <a href=\"http://example.com\" target=\"_top\">http://example.com</a> linked to via the <a href=\"http://rdfig.xmlhack.com/\">#rdfig weblog</a>, and had this thought: Thank goodness that <a href=\"http://www.netsol.com/cgi-bin/whois/whois?STRING=example.com&amp;SearchType=do\">someone</a> had thought to register that domain, or else my boss would have more likely than not been viewing porn after clicking on a link it in our last meeting.\n</p>","path":"2002/12/01/ooocci","content":"<p>Noticed <a href=\"http://example.com\" target=\"_top\">http://example.com</a> linked to via the <a href=\"http://rdfig.xmlhack.com/\">#rdfig weblog</a>, and had this thought: Thank goodness that <a href=\"http://www.netsol.com/cgi-bin/whois/whois?STRING=example.com&amp;SearchType=do\">someone</a> had thought to register that domain, or else my boss would have more likely than not been viewing porn after clicking on a link it in our last meeting.\n<!--more-->\nshortname=ooocci</p>\n<div id=\"comments\" class=\"comments archived-comments\">\n            <h3>Archived Comments</h3>\n\n        <ul class=\"comments\">\n\n        <li class=\"comment\" id=\"comment-221085195\">\n            <div class=\"meta\">\n                <div class=\"author\">\n                    <a class=\"avatar image\" rel=\"nofollow\" \n                       href=\"http://www.perceive.net\"><img src=\"http://www.gravatar.com/avatar.php?gravatar_id=9e76d0bf99487acc610624122a6317f3&amp;size=32&amp;default=http://mediacdn.disqus.com/1320279820/images/noavatar32.png\"/></a>\n                    <a class=\"avatar name\" rel=\"nofollow\" \n                       href=\"http://www.perceive.net\">Eric Vitiello</a>\n                </div>\n                <a href=\"#comment-221085195\" class=\"permalink\"><time datetime=\"2002-12-02T11:03:01\">2002-12-02T11:03:01</time></a>\n            </div>\n            <div class=\"content\">RFC2606 reserved example.com, example.net, example.org.. also test.xx invalid.xx and localhost.xx</div>\n\n<pre><code>    &lt;/li&gt;\n\n    &lt;li class=&quot;comment&quot; id=&quot;comment-221085196&quot;&gt;\n        &lt;div class=&quot;meta&quot;&gt;\n            &lt;div class=&quot;author&quot;&gt;\n                &lt;a class=&quot;avatar image&quot; rel=&quot;nofollow&quot; \n                   href=&quot;http://www.decafbad.com&quot;&gt;&lt;img src=&quot;http://www.gravatar.com/avatar.php?gravatar_id=2ac2cffd36ada8c734b90e02a1e5c1ac&amp;amp;size=32&amp;amp;default=http://mediacdn.disqus.com/1320279820/images/noavatar32.png&quot;/&gt;&lt;/a&gt;\n                &lt;a class=&quot;avatar name&quot; rel=&quot;nofollow&quot; \n                   href=&quot;http://www.decafbad.com&quot;&gt;l.m.orchard&lt;/a&gt;\n            &lt;/div&gt;\n            &lt;a href=&quot;#comment-221085196&quot; class=&quot;permalink&quot;&gt;&lt;time datetime=&quot;2002-12-02T13:22:51&quot;&gt;2002-12-02T13:22:51&lt;/time&gt;&lt;/a&gt;\n        &lt;/div&gt;\n        &lt;div class=&quot;content&quot;&gt;Things I feel like I should have known, but didn&#39;t.  Thanks for the pointer! :)&lt;/div&gt;\n\n    &lt;/li&gt;\n\n    &lt;li class=&quot;comment&quot; id=&quot;comment-221085198&quot;&gt;\n        &lt;div class=&quot;meta&quot;&gt;\n            &lt;div class=&quot;author&quot;&gt;\n                &lt;a class=&quot;avatar image&quot; rel=&quot;nofollow&quot; \n                   href=&quot;http://rc3.org/&quot;&gt;&lt;img src=&quot;http://www.gravatar.com/avatar.php?gravatar_id=818fa877485f2f6d119675a536217e6c&amp;amp;size=32&amp;amp;default=http://mediacdn.disqus.com/1320279820/images/noavatar32.png&quot;/&gt;&lt;/a&gt;\n                &lt;a class=&quot;avatar name&quot; rel=&quot;nofollow&quot; \n                   href=&quot;http://rc3.org/&quot;&gt;Rafe&lt;/a&gt;\n            &lt;/div&gt;\n            &lt;a href=&quot;#comment-221085198&quot; class=&quot;permalink&quot;&gt;&lt;time datetime=&quot;2002-12-02T13:47:41&quot;&gt;2002-12-02T13:47:41&lt;/time&gt;&lt;/a&gt;\n        &lt;/div&gt;\n        &lt;div class=&quot;content&quot;&gt;At one time, example.com was registered to someone and was used as something other than an example, despite the fact that the RFC clearly stated that the domain was reserved.  I don&#39;t know when it was returned to its proper usage, but it has been fixed for some time.&lt;/div&gt;\n\n    &lt;/li&gt;\n\n    &lt;li class=&quot;comment&quot; id=&quot;comment-221085200&quot;&gt;\n        &lt;div class=&quot;meta&quot;&gt;\n            &lt;div class=&quot;author&quot;&gt;\n                &lt;a class=&quot;avatar image&quot; rel=&quot;nofollow&quot; \n                   href=&quot;http://kalsey.com&quot;&gt;&lt;img src=&quot;http://www.gravatar.com/avatar.php?gravatar_id=79f874a58ccd440b448771ae1847d1d2&amp;amp;size=32&amp;amp;default=http://mediacdn.disqus.com/1320279820/images/noavatar32.png&quot;/&gt;&lt;/a&gt;\n                &lt;a class=&quot;avatar name&quot; rel=&quot;nofollow&quot; \n                   href=&quot;http://kalsey.com&quot;&gt;Adam Kalsey&lt;/a&gt;\n            &lt;/div&gt;\n            &lt;a href=&quot;#comment-221085200&quot; class=&quot;permalink&quot;&gt;&lt;time datetime=&quot;2002-12-02T15:02:05&quot;&gt;2002-12-02T15:02:05&lt;/time&gt;&lt;/a&gt;\n        &lt;/div&gt;\n        &lt;div class=&quot;content&quot;&gt;Searching Google for Localhost shows that there are many localhost.xx domains registered. localhost.net.au, localhost.be, localhost.net.ar...&lt;/div&gt;\n\n    &lt;/li&gt;\n\n    &lt;li class=&quot;comment&quot; id=&quot;comment-221085201&quot;&gt;\n        &lt;div class=&quot;meta&quot;&gt;\n            &lt;div class=&quot;author&quot;&gt;\n                &lt;a class=&quot;avatar image&quot; rel=&quot;nofollow&quot; \n                   href=&quot;http://InternetAlchemy.org&quot;&gt;&lt;img src=&quot;http://www.gravatar.com/avatar.php?gravatar_id=0fb9bcc795ab3784fa3e64e6d9dbc29d&amp;amp;size=32&amp;amp;default=http://mediacdn.disqus.com/1320279820/images/noavatar32.png&quot;/&gt;&lt;/a&gt;\n                &lt;a class=&quot;avatar name&quot; rel=&quot;nofollow&quot; \n                   href=&quot;http://InternetAlchemy.org&quot;&gt;Ian&lt;/a&gt;\n            &lt;/div&gt;\n            &lt;a href=&quot;#comment-221085201&quot; class=&quot;permalink&quot;&gt;&lt;time datetime=&quot;2002-12-10T10:26:14&quot;&gt;2002-12-10T10:26:14&lt;/time&gt;&lt;/a&gt;\n        &lt;/div&gt;\n        &lt;div class=&quot;content&quot;&gt;.test, .example, .invalid and .localhost are only reserved as top level domains. e.g. ian.test is reserved, but test.ian is not.&lt;/div&gt;\n\n    &lt;/li&gt;\n\n    &lt;/ul&gt;\n\n    &lt;/div&gt;\n</code></pre>"}