[
  {
    "comments_archived": true,
    "date": "2008-10-29T14:42:23.000Z",
    "layout": "post",
    "tags": [
      "webdev",
      "writing",
      "books",
      "entries",
      "jellystains",
      "webmasons",
      "webscientists",
      "webscience"
    ],
    "title": "Jelly Stains and Web Masons",
    "wordpress_id": 1424,
    "wordpress_slug": "jelly-stains-and-web-masons",
    "wordpress_url": "http://decafbad.com/blog/?p=1424",
    "year": "2008",
    "month": "10",
    "day": "29",
    "isDir": false,
    "slug": "jelly-stains-and-web-masons",
    "postName": "2008-10-29-jelly-stains-and-web-masons",
    "parentPath": "../blog.lmorchard.com/posts/archives/2008",
    "path": "2008/10/29/jelly-stains-and-web-masons",
    "prevPostPath": "2008/11/01/an-unnecessary-template-attribute-language",
    "nextPostPath": "2008/10/19/upgrades-versus-antiques"
  },
  {
    "comments_archived": true,
    "date": "2008-10-19T16:07:19.000Z",
    "layout": "post",
    "tags": [
      "apple",
      "hardware",
      "entries",
      "laptops",
      "personalcomputers",
      "pcs",
      "sustainability"
    ],
    "title": "Upgrades versus Antiques",
    "wordpress_id": 1407,
    "wordpress_slug": "upgrades-versus-antiques",
    "wordpress_url": "http://decafbad.com/blog/?p=1407",
    "year": "2008",
    "month": "10",
    "day": "19",
    "isDir": false,
    "slug": "upgrades-versus-antiques",
    "postName": "2008-10-19-upgrades-versus-antiques",
    "parentPath": "../blog.lmorchard.com/posts/archives/2008",
    "path": "2008/10/19/upgrades-versus-antiques",
    "prevPostPath": "2008/10/29/jelly-stains-and-web-masons",
    "nextPostPath": "2008/09/07/improving-my-delicious-command-for-ubiquity"
  }
]