[
  {
    "title": "Using SQLite as a document database for Mastodon exports",
    "tags": [
      "fediverse",
      "mastodon",
      "sqlite",
      "activitypub"
    ],
    "year": "2023",
    "month": "05",
    "day": "12",
    "isDir": true,
    "slug": "toots-in-sqlite",
    "date": "2023-05-12T12:00:00.000Z",
    "postName": "2023-05-12-toots-in-sqlite",
    "parentPath": "./content/posts/2023-05-12-toots-in-sqlite",
    "path": "2023/05/12/toots-in-sqlite",
    "thumbnail": "/blog.lmorchard.com/2023/05/12/toots-in-sqlite/cover.png",
    "summary": "TL;DR: SQLite has JSON functions, generated columns, and full-text search - which all seems like a perfect mix for ingesting exports from Mastodon for search!",
    "nextPostPath": "2023/02/06/the-machine-is-grieving"
  }
]