[
  {
    "title": "Biospheric Xenophobia",
    "author": "lmorchard",
    "layout": "post",
    "permalink": "/2012/07/03/biospheric-xenophobia",
    "dsq_thread_id": [
      1819111988
    ],
    "categories": [
      "Uncategorized"
    ],
    "tags": [
      "aliens",
      "fiction",
      "flashfiction",
      "scifi",
      "xenophobia"
    ],
    "year": "2012",
    "month": "07",
    "day": "03",
    "isDir": false,
    "slug": "biospheric-xenophobia",
    "date": "2012-07-03T12:00:00.000Z",
    "postName": "2012-07-03-biospheric-xenophobia",
    "parentPath": "./content/posts/archives/2012",
    "path": "2012/07/03/biospheric-xenophobia",
    "summary": "“Have you ever seen one of them?”",
    "prevPostPath": "2012/07/10/webdev-more-better",
    "nextPostPath": "2012/06/16/and-just-to-make-my-more-than-twitter"
  }
]