[
  {
    "title": "Building a New Creative Writing Habit",
    "tags": [
      "writing",
      "metablogging",
      "habits"
    ],
    "year": "2022",
    "month": "04",
    "day": "20",
    "isDir": true,
    "slug": "building-a-new-creative-writing-habit",
    "date": "2022-04-20T12:00:00.000Z",
    "postName": "2022-04-20-building-a-new-creative-writing-habit",
    "parentPath": "./content/posts/archives/2022/2022-04-20-building-a-new-creative-writing-habit",
    "path": "2022/04/20/building-a-new-creative-writing-habit",
    "thumbnail": "/blog.lmorchard.com/2022/04/20/building-a-new-creative-writing-habit/366BC739-E5C3-4ED6-B424-BEE08336110F.jpeg",
    "summary": "TL;DR: I'm trying to build a new creative writing habit. The immediate form that this has taken is a goal of writing 300 words of fiction per day that I post to my blog. I've been using 3-card spreads from a Tarot deck to supply writing prompts. I'm hoping I keep it up.",
    "prevPostPath": "2022/04/21/chemryths-hoard",
    "nextPostPath": "2022/04/20/korrines-hare"
  }
]